analogai/__init__.py
analogai-0.0.1.dist-info/LICENSE.txt
analogai-0.0.1.dist-info/METADATA
analogai-0.0.1.dist-info/WHEEL
analogai-0.0.1.dist-info/top_level.txt
analogai-0.0.1.dist-info/RECORD
